{
  "format_version": "1.12.0",
  "minecraft:geometry": [
    {
      "description": {
        "identifier": "geometry.lizard",
        "texture_width": 256,
        "texture_height": 256,
        "visible_bounds_width": 4,
        "visible_bounds_height": 4,
        "visible_bounds_offset": [
          0,
          1,
          0
        ]
      },
      "bones": [
        {
          "name": "body",
          "pivot": [
            0,
            13,
            -5
          ]
        },
        {
          "name": "tag_name",
          "pivot": [
            0,
            44,
            -17
          ],
          "parent": "body"
        },
        {
          "name": "chest",
          "pivot": [
            0,
            13.424999999999995,
            -5.434782227078088
          ],
          "parent": "body",
          "rotation": [
            14.999999999999996,
            0,
            0
          ],
          "cubes": [
            {
              "origin": [
                -5.5,
                5.924999999999999,
                -14.434782227078088
              ],
              "size": [
                11,
                13.000000000000009,
                15.000000000000004
              ],
              "uv": {
                "north": {
                  "uv": [
                    70,
                    46
                  ],
                  "uv_size": [
                    11,
                    13
                  ]
                },
                "east": {
                  "uv": [
                    16,
                    59
                  ],
                  "uv_size": [
                    15,
                    13
                  ]
                },
                "south": {
                  "uv": [
                    70,
                    32
                  ],
                  "uv_size": [
                    11,
                    13
                  ]
                },
                "west": {
                  "uv": [
                    16,
                    59
                  ],
                  "uv_size": [
                    15,
                    13
                  ]
                },
                "up": {
                  "uv": [
                    60,
                    0
                  ],
                  "uv_size": [
                    11,
                    15
                  ]
                },
                "down": {
                  "uv": [
                    60,
                    16
                  ],
                  "uv_size": [
                    11,
                    15
                  ]
                }
              },
              "pivot": [
                0,
                13.424999999999995,
                -5.434782227078088
              ],
              "inflate": 0.01
            },
            {
              "origin": [
                -5.5,
                7.343634123148802,
                -2.302826874894741
              ],
              "size": [
                11,
                13.000000000000007,
                10.000000000000004
              ],
              "uv": {
                "north": {
                  "uv": [
                    72,
                    14
                  ],
                  "uv_size": [
                    11,
                    13
                  ]
                },
                "east": {
                  "uv": [
                    72,
                    76
                  ],
                  "uv_size": [
                    10,
                    13
                  ]
                },
                "south": {
                  "uv": [
                    72,
                    0
                  ],
                  "uv_size": [
                    11,
                    13
                  ]
                },
                "west": {
                  "uv": [
                    72,
                    76
                  ],
                  "uv_size": [
                    10,
                    13
                  ]
                },
                "up": {
                  "uv": [
                    36,
                    86
                  ],
                  "uv_size": [
                    11,
                    10
                  ]
                },
                "down": {
                  "uv": [
                    83,
                    86
                  ],
                  "uv_size": [
                    11,
                    10
                  ]
                }
              },
              "pivot": [
                0,
                13.843634123148806,
                2.6971731251052624
              ],
              "rotation": [
                -22.5,
                0,
                0
              ],
              "inflate": -0.01
            }
          ]
        },
        {
          "name": "tail",
          "pivot": [
            -2.220446049250313e-16,
            21.467809311944276,
            4.933664869470541
          ],
          "parent": "chest",
          "cubes": [
            {
              "origin": [
                -4.5,
                15.089984035308177,
                6.80886992986014
              ],
              "size": [
                9,
                9.000000000000018,
                11
              ],
              "uv": {
                "north": {
                  "uv": [
                    34,
                    97
                  ],
                  "uv_size": [
                    9,
                    9
                  ]
                },
                "east": {
                  "uv": [
                    94,
                    46
                  ],
                  "uv_size": [
                    11,
                    9
                  ]
                },
                "south": {
                  "uv": [
                    44,
                    32
                  ],
                  "uv_size": [
                    9,
                    9
                  ]
                },
                "west": {
                  "uv": [
                    94,
                    46
                  ],
                  "uv_size": [
                    11,
                    9
                  ]
                },
                "up": {
                  "uv": [
                    95,
                    76
                  ],
                  "uv_size": [
                    9,
                    11
                  ]
                },
                "down": {
                  "uv": [
                    95,
                    88
                  ],
                  "uv_size": [
                    9,
                    11
                  ]
                }
              },
              "pivot": [
                1.0000000000000002,
                17.589984035308184,
                11.80886992986015
              ],
              "rotation": [
                -22.5,
                0,
                0
              ],
              "inflate": -0.01
            }
          ]
        },
        {
          "name": "tail_mid",
          "pivot": [
            2.0000000000000004,
            22.915493283085173,
            16.31833472122335
          ],
          "parent": "tail",
          "cubes": [
            {
              "origin": [
                -3.5,
                20.614108685323956,
                14.570525170603608
              ],
              "size": [
                7,
                7.000000000000007,
                14.99999999999998
              ],
              "uv": {
                "north": {
                  "uv": [
                    102,
                    121
                  ],
                  "uv_size": [
                    7,
                    7
                  ]
                },
                "east": {
                  "uv": [
                    0,
                    88
                  ],
                  "uv_size": [
                    15,
                    7
                  ]
                },
                "south": {
                  "uv": [
                    116,
                    66
                  ],
                  "uv_size": [
                    7,
                    7
                  ]
                },
                "west": {
                  "uv": [
                    0,
                    88
                  ],
                  "uv_size": [
                    15,
                    7
                  ]
                },
                "up": {
                  "uv": [
                    48,
                    89
                  ],
                  "uv_size": [
                    7,
                    15
                  ]
                },
                "down": {
                  "uv": [
                    56,
                    89
                  ],
                  "uv_size": [
                    7,
                    15
                  ]
                }
              },
              "pivot": [
                2,
                21.714108685323954,
                23.5705251706036
              ],
              "rotation": [
                -22.5,
                0,
                0
              ],
              "inflate": -0.01
            }
          ]
        },
        {
          "name": "tail_end",
          "pivot": [
            -1.0000000000000004,
            26.3978379060825,
            27.410001037747424
          ],
          "parent": "tail_mid",
          "cubes": [
            {
              "origin": [
                -2.4999999999999996,
                27.231953542045975,
                28.139854205226285
              ],
              "size": [
                5,
                5.000000000000025,
                15.000000000000007
              ],
              "uv": {
                "north": {
                  "uv": [
                    0,
                    132
                  ],
                  "uv_size": [
                    5,
                    5
                  ]
                },
                "east": {
                  "uv": [
                    8,
                    112
                  ],
                  "uv_size": [
                    15,
                    5
                  ]
                },
                "south": {
                  "uv": [
                    88,
                    104
                  ],
                  "uv_size": [
                    5,
                    5
                  ]
                },
                "west": {
                  "uv": [
                    8,
                    112
                  ],
                  "uv_size": [
                    15,
                    5
                  ]
                },
                "up": {
                  "uv": [
                    96,
                    110
                  ],
                  "uv_size": [
                    5,
                    15
                  ]
                },
                "down": {
                  "uv": [
                    24,
                    112
                  ],
                  "uv_size": [
                    5,
                    15
                  ]
                }
              },
              "pivot": [
                3,
                26.331953542045973,
                37.139854205226285
              ],
              "rotation": [
                -22.5,
                0,
                0
              ],
              "inflate": -0.01
            }
          ]
        },
        {
          "name": "tail_tip",
          "pivot": [
            -4.440892098500626e-16,
            31.207479564170676,
            41.04467050103069
          ],
          "parent": "tail_end",
          "cubes": [
            {
              "origin": [
                -1.4999999999999996,
                28.45213394051319,
                42.08657997851073
              ],
              "size": [
                3,
                3.0000000000000107,
                15.000000000000014
              ],
              "uv": {
                "north": {
                  "uv": [
                    32,
                    89
                  ],
                  "uv_size": [
                    3,
                    3
                  ]
                },
                "east": {
                  "uv": [
                    122,
                    74
                  ],
                  "uv_size": [
                    15,
                    3
                  ]
                },
                "south": {
                  "uv": [
                    12,
                    84
                  ],
                  "uv_size": [
                    3,
                    3
                  ]
                },
                "west": {
                  "uv": [
                    122,
                    74
                  ],
                  "uv_size": [
                    15,
                    3
                  ]
                },
                "up": {
                  "uv": [
                    122,
                    82
                  ],
                  "uv_size": [
                    3,
                    15
                  ]
                },
                "down": {
                  "uv": [
                    88,
                    122
                  ],
                  "uv_size": [
                    3,
                    15
                  ]
                }
              },
              "pivot": [
                4,
                26.331953542045973,
                37.139854205226285
              ],
              "rotation": [
                -22.5,
                0,
                0
              ],
              "inflate": -0.01
            }
          ]
        },
        {
          "name": "neck",
          "pivot": [
            0,
            5.958855371842635,
            -14.52357054100419
          ],
          "parent": "chest",
          "rotation": [
            -7.500000000000004,
            0,
            0
          ],
          "cubes": [
            {
              "origin": [
                -5.5,
                6.00840429971404,
                -14.58390151967324
              ],
              "size": [
                11,
                11.99999999999999,
                11.000000000000021
              ],
              "uv": {
                "north": {
                  "uv": [
                    48,
                    76
                  ],
                  "uv_size": [
                    11,
                    12
                  ]
                },
                "east": {
                  "uv": [
                    0,
                    75
                  ],
                  "uv_size": [
                    11,
                    12
                  ]
                },
                "south": {
                  "uv": [
                    36,
                    73
                  ],
                  "uv_size": [
                    11,
                    12
                  ]
                },
                "west": {
                  "uv": [
                    0,
                    75
                  ],
                  "uv_size": [
                    11,
                    12
                  ]
                },
                "up": {
                  "uv": [
                    84,
                    0
                  ],
                  "uv_size": [
                    11,
                    11
                  ]
                },
                "down": {
                  "uv": [
                    84,
                    12
                  ],
                  "uv_size": [
                    11,
                    11
                  ]
                }
              },
              "pivot": [
                0,
                6.341538804207728,
                -14.299691008492896
              ],
              "rotation": [
                -22.5,
                0,
                0
              ]
            },
            {
              "origin": [
                -4.5,
                18.64652440208131,
                -21.747158602109064
              ],
              "size": [
                9,
                2.9999999999999893,
                9.000000000000021
              ],
              "uv": {
                "north": {
                  "uv": [
                    84,
                    24
                  ],
                  "uv_size": [
                    9,
                    3
                  ]
                },
                "east": {
                  "uv": [
                    72,
                    28
                  ],
                  "uv_size": [
                    9,
                    3
                  ]
                },
                "south": {
                  "uv": [
                    70,
                    60
                  ],
                  "uv_size": [
                    9,
                    3
                  ]
                },
                "west": {
                  "uv": [
                    130,
                    98
                  ],
                  "uv_size": [
                    9,
                    3
                  ]
                },
                "up": {
                  "uv": [
                    95,
                    100
                  ],
                  "uv_size": [
                    9,
                    9
                  ]
                },
                "down": {
                  "uv": [
                    104,
                    12
                  ],
                  "uv_size": [
                    9,
                    9
                  ]
                }
              },
              "pivot": [
                0,
                24.646524402081297,
                -16.247158602109057
              ],
              "rotation": [
                -22.5,
                0,
                0
              ],
              "inflate": -0.01
            }
          ]
        },
        {
          "name": "h_head",
          "pivot": [
            2.775557561562894e-17,
            20.8381065406507,
            -17.136657870199453
          ],
          "parent": "neck",
          "rotation": [
            -27.499999999999954,
            0,
            0
          ],
          "cubes": [
            {
              "origin": [
                -4,
                23.560052135385778,
                -27.442196611710997
              ],
              "size": [
                7.999999999999999,
                4.999999999999986,
                8.000000000000028
              ],
              "uv": {
                "north": {
                  "uv": [
                    68,
                    126
                  ],
                  "uv_size": [
                    8,
                    5
                  ]
                },
                "east": {
                  "uv": [
                    59,
                    125
                  ],
                  "uv_size": [
                    8,
                    5
                  ]
                },
                "south": {
                  "uv": [
                    50,
                    125
                  ],
                  "uv_size": [
                    8,
                    5
                  ]
                },
                "west": {
                  "uv": [
                    126,
                    82
                  ],
                  "uv_size": [
                    8,
                    5
                  ]
                },
                "up": {
                  "uv": [
                    115,
                    39
                  ],
                  "uv_size": [
                    8,
                    8
                  ]
                },
                "down": {
                  "uv": [
                    79,
                    115
                  ],
                  "uv_size": [
                    8,
                    8
                  ]
                }
              },
              "pivot": [
                -2.220446049250313e-16,
                20.06005213538577,
                -23.442196611710983
              ],
              "rotation": [
                -22.5,
                0,
                0
              ]
            },
            {
              "origin": [
                -3.999999999999999,
                25.175187651084812,
                -30.490452476623048
              ],
              "size": [
                7.999999999999998,
                2.999999999999986,
                3.0000000000000284
              ],
              "uv": {
                "north": {
                  "uv": [
                    134,
                    54
                  ],
                  "uv_size": [
                    8,
                    3
                  ]
                },
                "east": {
                  "uv": [
                    91,
                    66
                  ],
                  "uv_size": [
                    3,
                    3
                  ]
                },
                "south": {
                  "uv": [
                    133,
                    50
                  ],
                  "uv_size": [
                    8,
                    3
                  ]
                },
                "west": {
                  "uv": [
                    91,
                    70
                  ],
                  "uv_size": [
                    3,
                    3
                  ]
                },
                "up": {
                  "uv": [
                    134,
                    58
                  ],
                  "uv_size": [
                    8,
                    3
                  ]
                },
                "down": {
                  "uv": [
                    134,
                    93
                  ],
                  "uv_size": [
                    8,
                    3
                  ]
                }
              },
              "pivot": [
                0.5000000000000002,
                25.6751876510848,
                -28.99045247662304
              ],
              "rotation": [
                45,
                0,
                0
              ],
              "inflate": -0.01
            },
            {
              "origin": [
                1.9416300899136147,
                27.9437621027849,
                -25.318664965485404
              ],
              "size": [
                4.000000000000032,
                2.9999999999999467,
                6.000000000000007
              ],
              "uv": {
                "north": {
                  "uv": [
                    147,
                    101
                  ],
                  "uv_size": [
                    4,
                    3
                  ]
                },
                "east": {
                  "uv": [
                    143,
                    135
                  ],
                  "uv_size": [
                    6,
                    3
                  ]
                },
                "south": {
                  "uv": [
                    84,
                    147
                  ],
                  "uv_size": [
                    4,
                    3
                  ]
                },
                "west": {
                  "uv": [
                    143,
                    139
                  ],
                  "uv_size": [
                    6,
                    3
                  ]
                },
                "up": {
                  "uv": [
                    135,
                    4
                  ],
                  "uv_size": [
                    4,
                    6
                  ]
                },
                "down": {
                  "uv": [
                    135,
                    20
                  ],
                  "uv_size": [
                    4,
                    6
                  ]
                }
              },
              "pivot": [
                5.8416300899136235,
                27.94376210278487,
                -21.318664965485397
              ],
              "rotation": [
                0,
                22.5,
                0
              ],
              "inflate": -0.01
            },
            {
              "origin": [
                1.9568541944248596,
                25.963762102337856,
                -22.24212828357432
              ],
              "size": [
                4.00000000000003,
                1.999999999999993,
                3.0000000000000036
              ],
              "uv": {
                "north": {
                  "uv": [
                    148,
                    69
                  ],
                  "uv_size": [
                    4,
                    2
                  ]
                },
                "east": {
                  "uv": [
                    131,
                    4
                  ],
                  "uv_size": [
                    3,
                    2
                  ]
                },
                "south": {
                  "uv": [
                    148,
                    28
                  ],
                  "uv_size": [
                    4,
                    2
                  ]
                },
                "west": {
                  "uv": [
                    140,
                    8
                  ],
                  "uv_size": [
                    3,
                    2
                  ]
                },
                "up": {
                  "uv": [
                    147,
                    105
                  ],
                  "uv_size": [
                    4,
                    3
                  ]
                },
                "down": {
                  "uv": [
                    147,
                    109
                  ],
                  "uv_size": [
                    4,
                    3
                  ]
                }
              },
              "pivot": [
                5.656854194424868,
                27.963762102337828,
                -21.24212828357432
              ],
              "rotation": [
                0,
                22.5,
                0
              ],
              "inflate": -0.01
            },
            {
              "origin": [
                1.9437885497026959,
                22.973762092801113,
                -25.247540228009676
              ],
              "size": [
                4.00000000000003,
                2.999999999999993,
                6.0000000000000036
              ],
              "uv": {
                "north": {
                  "uv": [
                    114,
                    147
                  ],
                  "uv_size": [
                    4,
                    3
                  ]
                },
                "east": {
                  "uv": [
                    143,
                    143
                  ],
                  "uv_size": [
                    6,
                    3
                  ]
                },
                "south": {
                  "uv": [
                    147,
                    113
                  ],
                  "uv_size": [
                    4,
                    3
                  ]
                },
                "west": {
                  "uv": [
                    144,
                    8
                  ],
                  "uv_size": [
                    6,
                    3
                  ]
                },
                "up": {
                  "uv": [
                    135,
                    27
                  ],
                  "uv_size": [
                    4,
                    6
                  ]
                },
                "down": {
                  "uv": [
                    65,
                    136
                  ],
                  "uv_size": [
                    4,
                    6
                  ]
                }
              },
              "pivot": [
                5.6437885497027045,
                27.973762092801085,
                -21.247540228009676
              ],
              "rotation": [
                0,
                22.5,
                0
              ]
            },
            {
              "origin": [
                1.9492005330766653,
                19.983762321682946,
                -25.260605856602943
              ],
              "size": [
                4.00000000000003,
                2.999999999999993,
                6.0000000000000036
              ],
              "uv": {
                "north": {
                  "uv": [
                    147,
                    147
                  ],
                  "uv_size": [
                    4,
                    3
                  ]
                },
                "east": {
                  "uv": [
                    144,
                    61
                  ],
                  "uv_size": [
                    6,
                    3
                  ]
                },
                "south": {
                  "uv": [
                    142,
                    147
                  ],
                  "uv_size": [
                    4,
                    3
                  ]
                },
                "west": {
                  "uv": [
                    144,
                    87
                  ],
                  "uv_size": [
                    6,
                    3
                  ]
                },
                "up": {
                  "uv": [
                    70,
                    136
                  ],
                  "uv_size": [
                    4,
                    6
                  ]
                },
                "down": {
                  "uv": [
                    75,
                    136
                  ],
                  "uv_size": [
                    4,
                    6
                  ]
                }
              },
              "pivot": [
                5.649200533076674,
                27.983762321682917,
                -21.260605856602943
              ],
              "rotation": [
                0,
                22.5,
                0
              ],
              "inflate": -0.01
            },
            {
              "origin": [
                -5.941630089913646,
                27.9437621027849,
                -25.318664965485404
              ],
              "size": [
                4.000000000000032,
                2.9999999999999467,
                6.000000000000007
              ],
              "uv": {
                "north": {
                  "uv": [
                    147,
                    101
                  ],
                  "uv_size": [
                    4,
                    3
                  ]
                },
                "east": {
                  "uv": [
                    143,
                    139
                  ],
                  "uv_size": [
                    6,
                    3
                  ]
                },
                "south": {
                  "uv": [
                    84,
                    147
                  ],
                  "uv_size": [
                    4,
                    3
                  ]
                },
                "west": {
                  "uv": [
                    143,
                    135
                  ],
                  "uv_size": [
                    6,
                    3
                  ]
                },
                "up": {
                  "uv": [
                    135,
                    4
                  ],
                  "uv_size": [
                    4,
                    6
                  ]
                },
                "down": {
                  "uv": [
                    135,
                    20
                  ],
                  "uv_size": [
                    4,
                    6
                  ]
                }
              },
              "pivot": [
                -5.8416300899136235,
                27.94376210278487,
                -21.318664965485397
              ],
              "rotation": [
                0,
                -22.5,
                0
              ],
              "inflate": -0.01
            },
            {
              "origin": [
                -5.9437885497027265,
                22.973762092801113,
                -25.247540228009676
              ],
              "size": [
                4.00000000000003,
                2.999999999999993,
                6.0000000000000036
              ],
              "uv": {
                "north": {
                  "uv": [
                    114,
                    147
                  ],
                  "uv_size": [
                    4,
                    3
                  ]
                },
                "east": {
                  "uv": [
                    144,
                    8
                  ],
                  "uv_size": [
                    6,
                    3
                  ]
                },
                "south": {
                  "uv": [
                    147,
                    113
                  ],
                  "uv_size": [
                    4,
                    3
                  ]
                },
                "west": {
                  "uv": [
                    143,
                    143
                  ],
                  "uv_size": [
                    6,
                    3
                  ]
                },
                "up": {
                  "uv": [
                    135,
                    27
                  ],
                  "uv_size": [
                    4,
                    6
                  ]
                },
                "down": {
                  "uv": [
                    65,
                    136
                  ],
                  "uv_size": [
                    4,
                    6
                  ]
                }
              },
              "pivot": [
                -5.6437885497027045,
                27.973762092801085,
                -21.247540228009676
              ],
              "rotation": [
                0,
                -22.5,
                0
              ]
            },
            {
              "origin": [
                -5.949200533076696,
                19.983762321682946,
                -25.260605856602943
              ],
              "size": [
                4.00000000000003,
                2.999999999999993,
                6.0000000000000036
              ],
              "uv": {
                "north": {
                  "uv": [
                    147,
                    147
                  ],
                  "uv_size": [
                    4,
                    3
                  ]
                },
                "east": {
                  "uv": [
                    144,
                    87
                  ],
                  "uv_size": [
                    6,
                    3
                  ]
                },
                "south": {
                  "uv": [
                    142,
                    147
                  ],
                  "uv_size": [
                    4,
                    3
                  ]
                },
                "west": {
                  "uv": [
                    144,
                    61
                  ],
                  "uv_size": [
                    6,
                    3
                  ]
                },
                "up": {
                  "uv": [
                    70,
                    136
                  ],
                  "uv_size": [
                    4,
                    6
                  ]
                },
                "down": {
                  "uv": [
                    75,
                    136
                  ],
                  "uv_size": [
                    4,
                    6
                  ]
                }
              },
              "pivot": [
                -5.649200533076674,
                27.983762321682917,
                -21.260605856602943
              ],
              "rotation": [
                0,
                -22.5,
                0
              ],
              "inflate": -0.01
            },
            {
              "origin": [
                -5.95685419442489,
                25.96376210233786,
                -22.24212828357432
              ],
              "size": [
                4.00000000000003,
                1.999999999999993,
                3.0000000000000036
              ],
              "uv": {
                "north": {
                  "uv": [
                    148,
                    69
                  ],
                  "uv_size": [
                    4,
                    2
                  ]
                },
                "east": {
                  "uv": [
                    140,
                    8
                  ],
                  "uv_size": [
                    3,
                    2
                  ]
                },
                "south": {
                  "uv": [
                    148,
                    28
                  ],
                  "uv_size": [
                    4,
                    2
                  ]
                },
                "west": {
                  "uv": [
                    131,
                    4
                  ],
                  "uv_size": [
                    3,
                    2
                  ]
                },
                "up": {
                  "uv": [
                    147,
                    105
                  ],
                  "uv_size": [
                    4,
                    3
                  ]
                },
                "down": {
                  "uv": [
                    147,
                    109
                  ],
                  "uv_size": [
                    4,
                    3
                  ]
                }
              },
              "pivot": [
                -5.656854194424868,
                27.96376210233783,
                -21.24212828357432
              ],
              "rotation": [
                0,
                -22.5,
                0
              ],
              "inflate": -0.01
            },
            {
              "origin": [
                -4.5,
                19.943762102784884,
                -24.652646168462795
              ],
              "size": [
                9,
                10.999999999999954,
                15.000000000000025
              ],
              "uv": {
                "north": {
                  "uv": [
                    96,
                    0
                  ],
                  "uv_size": [
                    9,
                    11
                  ]
                },
                "east": {
                  "uv": [
                    48,
                    64
                  ],
                  "uv_size": [
                    15,
                    11
                  ]
                },
                "south": {
                  "uv": [
                    0,
                    96
                  ],
                  "uv_size": [
                    9,
                    11
                  ]
                },
                "west": {
                  "uv": [
                    48,
                    64
                  ],
                  "uv_size": [
                    15,
                    11
                  ]
                },
                "up": {
                  "uv": [
                    16,
                    73
                  ],
                  "uv_size": [
                    9,
                    15
                  ]
                },
                "down": {
                  "uv": [
                    26,
                    73
                  ],
                  "uv_size": [
                    9,
                    15
                  ]
                }
              },
              "pivot": [
                2.4424906541753444e-15,
                25.443762102784884,
                -11.652646168462773
              ]
            },
            {
              "origin": [
                -5,
                19.762896981307723,
                -29.477106717529615
              ],
              "size": [
                10,
                3.999999999999986,
                7.000000000000021
              ],
              "uv": {
                "north": {
                  "uv": [
                    126,
                    88
                  ],
                  "uv_size": [
                    10,
                    4
                  ]
                },
                "east": {
                  "uv": [
                    104,
                    22
                  ],
                  "uv_size": [
                    7,
                    4
                  ]
                },
                "south": {
                  "uv": [
                    124,
                    69
                  ],
                  "uv_size": [
                    10,
                    4
                  ]
                },
                "west": {
                  "uv": [
                    126,
                    93
                  ],
                  "uv_size": [
                    7,
                    4
                  ]
                },
                "up": {
                  "uv": [
                    114,
                    23
                  ],
                  "uv_size": [
                    10,
                    7
                  ]
                },
                "down": {
                  "uv": [
                    114,
                    31
                  ],
                  "uv_size": [
                    10,
                    7
                  ]
                }
              },
              "pivot": [
                -0.4999999999999999,
                23.577108448809252,
                -21.823451418098756
              ]
            }
          ]
        },
        {
          "name": "mount",
          "pivot": [
            0,
            16,
            2
          ],
          "parent": "chest"
        },
        {
          "name": "right_frontleg",
          "pivot": [
            -5.5,
            18.825,
            -11.334782227078087
          ],
          "parent": "body",
          "cubes": [
            {
              "origin": [
                -9.825376037914419,
                10.362711609324753,
                -17.1599837711732
              ],
              "size": [
                7.0000000000000036,
                9.999999999999998,
                8
              ],
              "uv": {
                "north": {
                  "uv": [
                    114,
                    85
                  ],
                  "uv_size": [
                    7,
                    10
                  ]
                },
                "east": {
                  "uv": [
                    44,
                    105
                  ],
                  "uv_size": [
                    8,
                    10
                  ]
                },
                "south": {
                  "uv": [
                    114,
                    74
                  ],
                  "uv_size": [
                    7,
                    10
                  ]
                },
                "west": {
                  "uv": [
                    79,
                    104
                  ],
                  "uv_size": [
                    8,
                    10
                  ]
                },
                "up": {
                  "uv": [
                    116,
                    57
                  ],
                  "uv_size": [
                    7,
                    8
                  ]
                },
                "down": {
                  "uv": [
                    61,
                    116
                  ],
                  "uv_size": [
                    7,
                    8
                  ]
                }
              },
              "pivot": [
                1.6746239620855843,
                13.862711609324752,
                -6.159983771173196
              ]
            }
          ]
        },
        {
          "name": "right_backarm",
          "pivot": [
            -5.595640531145677,
            11.760265867057594,
            -12.074665442996029
          ],
          "parent": "right_frontleg",
          "cubes": [
            {
              "origin": [
                -8.02401037129175,
                1.6570360787916543,
                -14.410261644794428
              ],
              "size": [
                3.999999999999999,
                11,
                5
              ],
              "uv": {
                "north": {
                  "uv": [
                    124,
                    57
                  ],
                  "uv_size": [
                    4,
                    11
                  ]
                },
                "east": {
                  "uv": [
                    30,
                    118
                  ],
                  "uv_size": [
                    5,
                    11
                  ]
                },
                "south": {
                  "uv": [
                    122,
                    115
                  ],
                  "uv_size": [
                    4,
                    11
                  ]
                },
                "west": {
                  "uv": [
                    16,
                    118
                  ],
                  "uv_size": [
                    5,
                    11
                  ]
                },
                "up": {
                  "uv": [
                    108,
                    140
                  ],
                  "uv_size": [
                    4,
                    5
                  ]
                },
                "down": {
                  "uv": [
                    113,
                    140
                  ],
                  "uv_size": [
                    4,
                    5
                  ]
                }
              },
              "pivot": [
                0.5759896287082489,
                14.157036078791654,
                -5.410261644794422
              ]
            }
          ]
        },
        {
          "name": "right_hand",
          "pivot": [
            -6.479197514927359,
            3.966960526162315,
            -12.079779347279779
          ],
          "parent": "right_backarm",
          "cubes": [
            {
              "origin": [
                -9.181175164843918,
                0.7555539506184263,
                -15.449074850017654
              ],
              "size": [
                6.000000000000007,
                3.9999999999999947,
                6.000000000000011
              ],
              "uv": {
                "north": {
                  "uv": [
                    135,
                    69
                  ],
                  "uv_size": [
                    6,
                    4
                  ]
                },
                "east": {
                  "uv": [
                    135,
                    82
                  ],
                  "uv_size": [
                    6,
                    4
                  ]
                },
                "south": {
                  "uv": [
                    99,
                    41
                  ],
                  "uv_size": [
                    6,
                    4
                  ]
                },
                "west": {
                  "uv": [
                    134,
                    116
                  ],
                  "uv_size": [
                    6,
                    4
                  ]
                },
                "up": {
                  "uv": [
                    92,
                    126
                  ],
                  "uv_size": [
                    6,
                    6
                  ]
                },
                "down": {
                  "uv": [
                    6,
                    127
                  ],
                  "uv_size": [
                    6,
                    6
                  ]
                }
              },
              "pivot": [
                -6.1397551752698085,
                3.068976173624075,
                -11.714193298616417
              ],
              "rotation": [
                22.5,
                0,
                0
              ]
            },
            {
              "origin": [
                -8.139755175269803,
                -0.6280801012236368,
                -18.904142792277586
              ],
              "size": [
                3.9999999999999964,
                2.9999999999999982,
                7.000000000000002
              ],
              "uv": {
                "north": {
                  "uv": [
                    148,
                    4
                  ],
                  "uv_size": [
                    4,
                    3
                  ]
                },
                "east": {
                  "uv": [
                    48,
                    139
                  ],
                  "uv_size": [
                    7,
                    3
                  ]
                },
                "south": {
                  "uv": [
                    148,
                    0
                  ],
                  "uv_size": [
                    4,
                    3
                  ]
                },
                "west": {
                  "uv": [
                    40,
                    139
                  ],
                  "uv_size": [
                    7,
                    3
                  ]
                },
                "up": {
                  "uv": [
                    104,
                    129
                  ],
                  "uv_size": [
                    4,
                    7
                  ]
                },
                "down": {
                  "uv": [
                    129,
                    105
                  ],
                  "uv_size": [
                    4,
                    7
                  ]
                }
              },
              "pivot": [
                0.7602448247301937,
                13.871919898776367,
                -5.704142792277581
              ],
              "inflate": -0.011
            },
            {
              "origin": [
                -9.139755175269805,
                -0.6280801012236368,
                -12.904142792277588
              ],
              "size": [
                6.000000000000003,
                2.9999999999999982,
                3.0000000000000036
              ],
              "uv": {
                "north": {
                  "uv": [
                    144,
                    129
                  ],
                  "uv_size": [
                    6,
                    3
                  ]
                },
                "east": {
                  "uv": [
                    44,
                    97
                  ],
                  "uv_size": [
                    3,
                    3
                  ]
                },
                "south": {
                  "uv": [
                    92,
                    144
                  ],
                  "uv_size": [
                    6,
                    3
                  ]
                },
                "west": {
                  "uv": [
                    32,
                    93
                  ],
                  "uv_size": [
                    3,
                    3
                  ]
                },
                "up": {
                  "uv": [
                    77,
                    145
                  ],
                  "uv_size": [
                    6,
                    3
                  ]
                },
                "down": {
                  "uv": [
                    123,
                    145
                  ],
                  "uv_size": [
                    6,
                    3
                  ]
                }
              },
              "pivot": [
                0.7602448247301937,
                13.871919898776367,
                -5.704142792277581
              ],
              "inflate": -0.01
            },
            {
              "origin": [
                -10.901389961572413,
                -0.6280800389464685,
                -17.624473269821426
              ],
              "size": [
                3.000000000000007,
                2.999999999999999,
                7.999999999999995
              ],
              "uv": {
                "north": {
                  "uv": [
                    30,
                    112
                  ],
                  "uv_size": [
                    3,
                    3
                  ]
                },
                "east": {
                  "uv": [
                    109,
                    136
                  ],
                  "uv_size": [
                    8,
                    3
                  ]
                },
                "south": {
                  "uv": [
                    44,
                    101
                  ],
                  "uv_size": [
                    3,
                    3
                  ]
                },
                "west": {
                  "uv": [
                    135,
                    11
                  ],
                  "uv_size": [
                    8,
                    3
                  ]
                },
                "up": {
                  "uv": [
                    12,
                    75
                  ],
                  "uv_size": [
                    3,
                    8
                  ]
                },
                "down": {
                  "uv": [
                    18,
                    130
                  ],
                  "uv_size": [
                    3,
                    8
                  ]
                }
              },
              "pivot": [
                -10.220835422837903,
                1.3659003064912048,
                -14.092476943423291
              ],
              "rotation": [
                0,
                22.5,
                0
              ]
            },
            {
              "origin": [
                -3.4238214323880087,
                -0.6280800389464667,
                -12.422059417391429
              ],
              "size": [
                3.0000000000000084,
                2.9999999999999982,
                7.999999999999994
              ],
              "uv": {
                "north": {
                  "uv": [
                    100,
                    139
                  ],
                  "uv_size": [
                    3,
                    3
                  ]
                },
                "east": {
                  "uv": [
                    134,
                    136
                  ],
                  "uv_size": [
                    8,
                    3
                  ]
                },
                "south": {
                  "uv": [
                    92,
                    122
                  ],
                  "uv_size": [
                    3,
                    3
                  ]
                },
                "west": {
                  "uv": [
                    125,
                    136
                  ],
                  "uv_size": [
                    8,
                    3
                  ]
                },
                "up": {
                  "uv": [
                    80,
                    136
                  ],
                  "uv_size": [
                    3,
                    8
                  ]
                },
                "down": {
                  "uv": [
                    84,
                    136
                  ],
                  "uv_size": [
                    3,
                    8
                  ]
                }
              },
              "pivot": [
                11.495624028877494,
                1.3659003064912065,
                -13.890063090993296
              ],
              "rotation": [
                0,
                -22.5,
                0
              ]
            }
          ]
        },
        {
          "name": "left_frontleg",
          "pivot": [
            5.5,
            18.825,
            -11.334782227078087
          ],
          "parent": "body",
          "cubes": [
            {
              "origin": [
                2.825376037914415,
                10.362711609324753,
                -17.1599837711732
              ],
              "size": [
                7.0000000000000036,
                9.999999999999998,
                8
              ],
              "uv": {
                "north": {
                  "uv": [
                    114,
                    85
                  ],
                  "uv_size": [
                    7,
                    10
                  ]
                },
                "east": {
                  "uv": [
                    79,
                    104
                  ],
                  "uv_size": [
                    8,
                    10
                  ]
                },
                "south": {
                  "uv": [
                    114,
                    74
                  ],
                  "uv_size": [
                    7,
                    10
                  ]
                },
                "west": {
                  "uv": [
                    44,
                    105
                  ],
                  "uv_size": [
                    8,
                    10
                  ]
                },
                "up": {
                  "uv": [
                    116,
                    57
                  ],
                  "uv_size": [
                    7,
                    8
                  ]
                },
                "down": {
                  "uv": [
                    61,
                    116
                  ],
                  "uv_size": [
                    7,
                    8
                  ]
                }
              },
              "pivot": [
                -1.6746239620855843,
                13.862711609324752,
                -6.159983771173196
              ]
            }
          ]
        },
        {
          "name": "left_backarm",
          "pivot": [
            5.595640531145677,
            11.760265867057594,
            -12.074665442996029
          ],
          "parent": "left_frontleg",
          "cubes": [
            {
              "origin": [
                4.024010371291751,
                1.6570360787916543,
                -14.410261644794428
              ],
              "size": [
                3.999999999999999,
                11,
                5
              ],
              "uv": {
                "north": {
                  "uv": [
                    124,
                    57
                  ],
                  "uv_size": [
                    4,
                    11
                  ]
                },
                "east": {
                  "uv": [
                    16,
                    118
                  ],
                  "uv_size": [
                    5,
                    11
                  ]
                },
                "south": {
                  "uv": [
                    122,
                    115
                  ],
                  "uv_size": [
                    4,
                    11
                  ]
                },
                "west": {
                  "uv": [
                    30,
                    118
                  ],
                  "uv_size": [
                    5,
                    11
                  ]
                },
                "up": {
                  "uv": [
                    108,
                    140
                  ],
                  "uv_size": [
                    4,
                    5
                  ]
                },
                "down": {
                  "uv": [
                    113,
                    140
                  ],
                  "uv_size": [
                    4,
                    5
                  ]
                }
              },
              "pivot": [
                -0.5759896287082489,
                14.157036078791654,
                -5.410261644794422
              ]
            }
          ]
        },
        {
          "name": "left_hand",
          "pivot": [
            6.479197514927359,
            3.966960526162315,
            -12.079779347279779
          ],
          "parent": "left_backarm",
          "cubes": [
            {
              "origin": [
                3.1811751648439106,
                0.7555539506184263,
                -15.449074850017654
              ],
              "size": [
                6.000000000000007,
                3.9999999999999947,
                6.000000000000011
              ],
              "uv": {
                "north": {
                  "uv": [
                    135,
                    69
                  ],
                  "uv_size": [
                    6,
                    4
                  ]
                },
                "east": {
                  "uv": [
                    134,
                    116
                  ],
                  "uv_size": [
                    6,
                    4
                  ]
                },
                "south": {
                  "uv": [
                    99,
                    41
                  ],
                  "uv_size": [
                    6,
                    4
                  ]
                },
                "west": {
                  "uv": [
                    135,
                    82
                  ],
                  "uv_size": [
                    6,
                    4
                  ]
                },
                "up": {
                  "uv": [
                    92,
                    126
                  ],
                  "uv_size": [
                    6,
                    6
                  ]
                },
                "down": {
                  "uv": [
                    6,
                    127
                  ],
                  "uv_size": [
                    6,
                    6
                  ]
                }
              },
              "pivot": [
                6.1397551752698085,
                3.068976173624075,
                -11.714193298616417
              ],
              "rotation": [
                22.5,
                0,
                0
              ]
            },
            {
              "origin": [
                4.139755175269807,
                -0.6280801012236368,
                -18.904142792277586
              ],
              "size": [
                3.9999999999999964,
                2.9999999999999982,
                7.000000000000002
              ],
              "uv": {
                "north": {
                  "uv": [
                    148,
                    4
                  ],
                  "uv_size": [
                    4,
                    3
                  ]
                },
                "east": {
                  "uv": [
                    40,
                    139
                  ],
                  "uv_size": [
                    7,
                    3
                  ]
                },
                "south": {
                  "uv": [
                    148,
                    0
                  ],
                  "uv_size": [
                    4,
                    3
                  ]
                },
                "west": {
                  "uv": [
                    48,
                    139
                  ],
                  "uv_size": [
                    7,
                    3
                  ]
                },
                "up": {
                  "uv": [
                    104,
                    129
                  ],
                  "uv_size": [
                    4,
                    7
                  ]
                },
                "down": {
                  "uv": [
                    129,
                    105
                  ],
                  "uv_size": [
                    4,
                    7
                  ]
                }
              },
              "pivot": [
                -0.7602448247301937,
                13.871919898776367,
                -5.704142792277581
              ],
              "inflate": -0.011
            },
            {
              "origin": [
                3.1397551752698023,
                -0.6280801012236368,
                -12.904142792277588
              ],
              "size": [
                6.000000000000003,
                2.9999999999999982,
                3.0000000000000036
              ],
              "uv": {
                "north": {
                  "uv": [
                    144,
                    129
                  ],
                  "uv_size": [
                    6,
                    3
                  ]
                },
                "east": {
                  "uv": [
                    32,
                    93
                  ],
                  "uv_size": [
                    3,
                    3
                  ]
                },
                "south": {
                  "uv": [
                    92,
                    144
                  ],
                  "uv_size": [
                    6,
                    3
                  ]
                },
                "west": {
                  "uv": [
                    44,
                    97
                  ],
                  "uv_size": [
                    3,
                    3
                  ]
                },
                "up": {
                  "uv": [
                    77,
                    145
                  ],
                  "uv_size": [
                    6,
                    3
                  ]
                },
                "down": {
                  "uv": [
                    123,
                    145
                  ],
                  "uv_size": [
                    6,
                    3
                  ]
                }
              },
              "pivot": [
                -0.7602448247301937,
                13.871919898776367,
                -5.704142792277581
              ],
              "inflate": -0.01
            },
            {
              "origin": [
                7.901389961572406,
                -0.6280800389464685,
                -17.624473269821426
              ],
              "size": [
                3.000000000000007,
                2.999999999999999,
                7.999999999999995
              ],
              "uv": {
                "north": {
                  "uv": [
                    30,
                    112
                  ],
                  "uv_size": [
                    3,
                    3
                  ]
                },
                "east": {
                  "uv": [
                    135,
                    11
                  ],
                  "uv_size": [
                    8,
                    3
                  ]
                },
                "south": {
                  "uv": [
                    44,
                    101
                  ],
                  "uv_size": [
                    3,
                    3
                  ]
                },
                "west": {
                  "uv": [
                    109,
                    136
                  ],
                  "uv_size": [
                    8,
                    3
                  ]
                },
                "up": {
                  "uv": [
                    12,
                    75
                  ],
                  "uv_size": [
                    3,
                    8
                  ]
                },
                "down": {
                  "uv": [
                    18,
                    130
                  ],
                  "uv_size": [
                    3,
                    8
                  ]
                }
              },
              "pivot": [
                10.220835422837903,
                1.3659003064912048,
                -14.092476943423291
              ],
              "rotation": [
                0,
                -22.5,
                0
              ]
            },
            {
              "origin": [
                0.42382143238800046,
                -0.6280800389464667,
                -12.422059417391429
              ],
              "size": [
                3.0000000000000084,
                2.9999999999999982,
                7.999999999999994
              ],
              "uv": {
                "north": {
                  "uv": [
                    100,
                    139
                  ],
                  "uv_size": [
                    3,
                    3
                  ]
                },
                "east": {
                  "uv": [
                    125,
                    136
                  ],
                  "uv_size": [
                    8,
                    3
                  ]
                },
                "south": {
                  "uv": [
                    92,
                    122
                  ],
                  "uv_size": [
                    3,
                    3
                  ]
                },
                "west": {
                  "uv": [
                    134,
                    136
                  ],
                  "uv_size": [
                    8,
                    3
                  ]
                },
                "up": {
                  "uv": [
                    80,
                    136
                  ],
                  "uv_size": [
                    3,
                    8
                  ]
                },
                "down": {
                  "uv": [
                    84,
                    136
                  ],
                  "uv_size": [
                    3,
                    8
                  ]
                }
              },
              "pivot": [
                -11.495624028877494,
                1.3659003064912065,
                -13.890063090993296
              ],
              "rotation": [
                0,
                22.5,
                0
              ]
            }
          ]
        },
        {
          "name": "right_backleg",
          "pivot": [
            -4.0999999999999925,
            13.725000000000003,
            3.565217772921912
          ],
          "parent": "body",
          "cubes": [
            {
              "origin": [
                -8.289303414263193,
                5.082277045569948,
                0.4902090301414368
              ],
              "size": [
                8.000000000000002,
                10,
                7.999999999999999
              ],
              "uv": {
                "north": {
                  "uv": [
                    105,
                    98
                  ],
                  "uv_size": [
                    8,
                    10
                  ]
                },
                "east": {
                  "uv": [
                    106,
                    0
                  ],
                  "uv_size": [
                    8,
                    10
                  ]
                },
                "south": {
                  "uv": [
                    105,
                    76
                  ],
                  "uv_size": [
                    8,
                    10
                  ]
                },
                "west": {
                  "uv": [
                    105,
                    87
                  ],
                  "uv_size": [
                    8,
                    10
                  ]
                },
                "up": {
                  "uv": [
                    113,
                    115
                  ],
                  "uv_size": [
                    8,
                    8
                  ]
                },
                "down": {
                  "uv": [
                    43,
                    116
                  ],
                  "uv_size": [
                    8,
                    8
                  ]
                }
              },
              "pivot": [
                -3.2893034142631867,
                8.082277045569949,
                6.490209030141439
              ]
            }
          ]
        },
        {
          "name": "right_fronttibia",
          "pivot": [
            -3.232362043742962,
            5.79175967541695,
            4.0824000489802295
          ],
          "parent": "right_backleg",
          "cubes": [
            {
              "origin": [
                -7.185004266227214,
                2.513960916797807,
                2.554114327590194
              ],
              "size": [
                7.000000000000006,
                5.9999999999999964,
                14.000000000000002
              ],
              "uv": {
                "north": {
                  "uv": [
                    123,
                    0
                  ],
                  "uv_size": [
                    7,
                    6
                  ]
                },
                "east": {
                  "uv": [
                    64,
                    98
                  ],
                  "uv_size": [
                    14,
                    6
                  ]
                },
                "south": {
                  "uv": [
                    122,
                    98
                  ],
                  "uv_size": [
                    7,
                    6
                  ]
                },
                "west": {
                  "uv": [
                    80,
                    97
                  ],
                  "uv_size": [
                    14,
                    6
                  ]
                },
                "up": {
                  "uv": [
                    96,
                    12
                  ],
                  "uv_size": [
                    7,
                    14
                  ]
                },
                "down": {
                  "uv": [
                    10,
                    97
                  ],
                  "uv_size": [
                    7,
                    14
                  ]
                }
              },
              "pivot": [
                -2.18500426622721,
                9.513960916797803,
                5.5541143275901925
              ]
            }
          ]
        },
        {
          "name": "right_frontfoot",
          "pivot": [
            -3.7483693285910804,
            7.4647606016683445,
            17.06590589842097
          ],
          "parent": "right_fronttibia",
          "cubes": [
            {
              "origin": [
                -7.248369328591081,
                -3.0352393983316563,
                15.565905898420969
              ],
              "size": [
                7.0000000000000036,
                10.999999999999995,
                4
              ],
              "uv": {
                "north": {
                  "uv": [
                    0,
                    108
                  ],
                  "uv_size": [
                    7,
                    11
                  ]
                },
                "east": {
                  "uv": [
                    115,
                    124
                  ],
                  "uv_size": [
                    4,
                    11
                  ]
                },
                "south": {
                  "uv": [
                    71,
                    105
                  ],
                  "uv_size": [
                    7,
                    11
                  ]
                },
                "west": {
                  "uv": [
                    110,
                    124
                  ],
                  "uv_size": [
                    4,
                    11
                  ]
                },
                "up": {
                  "uv": [
                    129,
                    64
                  ],
                  "uv_size": [
                    7,
                    4
                  ]
                },
                "down": {
                  "uv": [
                    130,
                    15
                  ],
                  "uv_size": [
                    7,
                    4
                  ]
                }
              },
              "pivot": [
                -2.2483693285910777,
                8.964760601668338,
                6.565905898420962
              ]
            }
          ]
        },
        {
          "name": "right_toes",
          "pivot": [
            -2.748369328591083,
            -1.5352393983316632,
            20.065905898420972
          ],
          "parent": "right_frontfoot",
          "cubes": [
            {
              "origin": [
                -9.03121172703092,
                -3.0352393983316563,
                12.39900121002471
              ],
              "size": [
                4.000000000000005,
                2.9999999999999987,
                7
              ],
              "uv": {
                "north": {
                  "uv": [
                    19,
                    148
                  ],
                  "uv_size": [
                    4,
                    3
                  ]
                },
                "east": {
                  "uv": [
                    139,
                    110
                  ],
                  "uv_size": [
                    7,
                    3
                  ]
                },
                "south": {
                  "uv": [
                    148,
                    16
                  ],
                  "uv_size": [
                    4,
                    3
                  ]
                },
                "west": {
                  "uv": [
                    139,
                    106
                  ],
                  "uv_size": [
                    7,
                    3
                  ]
                },
                "up": {
                  "uv": [
                    130,
                    20
                  ],
                  "uv_size": [
                    4,
                    7
                  ]
                },
                "down": {
                  "uv": [
                    27,
                    130
                  ],
                  "uv_size": [
                    4,
                    7
                  ]
                }
              },
              "pivot": [
                -5.931211727030921,
                -1.5352393983316595,
                15.89900121002471
              ],
              "rotation": [
                0,
                45,
                0
              ]
            },
            {
              "origin": [
                2.5837162377057137,
                -3.035239398331657,
                22.691894428838165
              ],
              "size": [
                4.000000000000002,
                2.999999999999999,
                6.999999999999993
              ],
              "uv": {
                "north": {
                  "uv": [
                    148,
                    24
                  ],
                  "uv_size": [
                    4,
                    3
                  ]
                },
                "east": {
                  "uv": [
                    140,
                    19
                  ],
                  "uv_size": [
                    7,
                    3
                  ]
                },
                "south": {
                  "uv": [
                    148,
                    20
                  ],
                  "uv_size": [
                    4,
                    3
                  ]
                },
                "west": {
                  "uv": [
                    140,
                    4
                  ],
                  "uv_size": [
                    7,
                    3
                  ]
                },
                "up": {
                  "uv": [
                    130,
                    28
                  ],
                  "uv_size": [
                    4,
                    7
                  ]
                },
                "down": {
                  "uv": [
                    32,
                    130
                  ],
                  "uv_size": [
                    4,
                    7
                  ]
                }
              },
              "pivot": [
                13.483716237705726,
                -1.5352393983316597,
                15.191894428838168
              ],
              "rotation": [
                0,
                -45,
                0
              ]
            },
            {
              "origin": [
                -5.648369328591082,
                -3.0352393983316563,
                11.565905898420958
              ],
              "size": [
                4.000000000000003,
                2.9999999999999987,
                9.00000000000001
              ],
              "uv": {
                "north": {
                  "uv": [
                    42,
                    148
                  ],
                  "uv_size": [
                    4,
                    3
                  ]
                },
                "east": {
                  "uv": [
                    132,
                    126
                  ],
                  "uv_size": [
                    9,
                    3
                  ]
                },
                "south": {
                  "uv": [
                    37,
                    148
                  ],
                  "uv_size": [
                    4,
                    3
                  ]
                },
                "west": {
                  "uv": [
                    132,
                    122
                  ],
                  "uv_size": [
                    9,
                    3
                  ]
                },
                "up": {
                  "uv": [
                    127,
                    122
                  ],
                  "uv_size": [
                    4,
                    9
                  ]
                },
                "down": {
                  "uv": [
                    22,
                    128
                  ],
                  "uv_size": [
                    4,
                    9
                  ]
                }
              },
              "pivot": [
                13.25163067140892,
                -1.5352393983316597,
                16.06590589842097
              ],
              "inflate": 0.01
            }
          ]
        },
        {
          "name": "left_backleg",
          "pivot": [
            4.0999999999999925,
            13.725000000000003,
            3.565217772921912
          ],
          "parent": "body",
          "cubes": [
            {
              "origin": [
                0.2893034142631909,
                5.082277045569948,
                0.4902090301414368
              ],
              "size": [
                8.000000000000002,
                10,
                7.999999999999999
              ],
              "uv": {
                "north": {
                  "uv": [
                    105,
                    98
                  ],
                  "uv_size": [
                    8,
                    10
                  ]
                },
                "east": {
                  "uv": [
                    105,
                    87
                  ],
                  "uv_size": [
                    8,
                    10
                  ]
                },
                "south": {
                  "uv": [
                    105,
                    76
                  ],
                  "uv_size": [
                    8,
                    10
                  ]
                },
                "west": {
                  "uv": [
                    106,
                    0
                  ],
                  "uv_size": [
                    8,
                    10
                  ]
                },
                "up": {
                  "uv": [
                    113,
                    115
                  ],
                  "uv_size": [
                    8,
                    8
                  ]
                },
                "down": {
                  "uv": [
                    43,
                    116
                  ],
                  "uv_size": [
                    8,
                    8
                  ]
                }
              },
              "pivot": [
                3.2893034142631867,
                8.082277045569949,
                6.490209030141439
              ]
            }
          ]
        },
        {
          "name": "left_fronttibia",
          "pivot": [
            3.232362043742962,
            5.79175967541695,
            4.0824000489802295
          ],
          "parent": "left_backleg",
          "cubes": [
            {
              "origin": [
                0.1850042662272079,
                2.513960916797807,
                2.554114327590194
              ],
              "size": [
                7.000000000000006,
                5.9999999999999964,
                14.000000000000002
              ],
              "uv": {
                "north": {
                  "uv": [
                    123,
                    0
                  ],
                  "uv_size": [
                    7,
                    6
                  ]
                },
                "east": {
                  "uv": [
                    80,
                    97
                  ],
                  "uv_size": [
                    14,
                    6
                  ]
                },
                "south": {
                  "uv": [
                    122,
                    98
                  ],
                  "uv_size": [
                    7,
                    6
                  ]
                },
                "west": {
                  "uv": [
                    64,
                    98
                  ],
                  "uv_size": [
                    14,
                    6
                  ]
                },
                "up": {
                  "uv": [
                    96,
                    12
                  ],
                  "uv_size": [
                    7,
                    14
                  ]
                },
                "down": {
                  "uv": [
                    10,
                    97
                  ],
                  "uv_size": [
                    7,
                    14
                  ]
                }
              },
              "pivot": [
                2.18500426622721,
                9.513960916797803,
                5.5541143275901925
              ]
            }
          ]
        },
        {
          "name": "left_frontfoot",
          "pivot": [
            3.7483693285910804,
            7.4647606016683445,
            17.06590589842097
          ],
          "parent": "left_fronttibia",
          "cubes": [
            {
              "origin": [
                0.24836932859107758,
                -3.0352393983316563,
                15.565905898420969
              ],
              "size": [
                7.0000000000000036,
                10.999999999999995,
                4
              ],
              "uv": {
                "north": {
                  "uv": [
                    0,
                    108
                  ],
                  "uv_size": [
                    7,
                    11
                  ]
                },
                "east": {
                  "uv": [
                    110,
                    124
                  ],
                  "uv_size": [
                    4,
                    11
                  ]
                },
                "south": {
                  "uv": [
                    71,
                    105
                  ],
                  "uv_size": [
                    7,
                    11
                  ]
                },
                "west": {
                  "uv": [
                    115,
                    124
                  ],
                  "uv_size": [
                    4,
                    11
                  ]
                },
                "up": {
                  "uv": [
                    129,
                    64
                  ],
                  "uv_size": [
                    7,
                    4
                  ]
                },
                "down": {
                  "uv": [
                    130,
                    15
                  ],
                  "uv_size": [
                    7,
                    4
                  ]
                }
              },
              "pivot": [
                2.2483693285910777,
                8.964760601668338,
                6.565905898420962
              ]
            }
          ]
        },
        {
          "name": "left_toes",
          "pivot": [
            2.748369328591083,
            -1.5352393983316632,
            20.065905898420972
          ],
          "parent": "left_frontfoot",
          "cubes": [
            {
              "origin": [
                5.0312117270309145,
                -3.0352393983316563,
                12.39900121002471
              ],
              "size": [
                4.000000000000005,
                2.9999999999999987,
                7
              ],
              "uv": {
                "north": {
                  "uv": [
                    19,
                    148
                  ],
                  "uv_size": [
                    4,
                    3
                  ]
                },
                "east": {
                  "uv": [
                    139,
                    106
                  ],
                  "uv_size": [
                    7,
                    3
                  ]
                },
                "south": {
                  "uv": [
                    148,
                    16
                  ],
                  "uv_size": [
                    4,
                    3
                  ]
                },
                "west": {
                  "uv": [
                    139,
                    110
                  ],
                  "uv_size": [
                    7,
                    3
                  ]
                },
                "up": {
                  "uv": [
                    130,
                    20
                  ],
                  "uv_size": [
                    4,
                    7
                  ]
                },
                "down": {
                  "uv": [
                    27,
                    130
                  ],
                  "uv_size": [
                    4,
                    7
                  ]
                }
              },
              "pivot": [
                5.931211727030921,
                -1.5352393983316595,
                15.89900121002471
              ],
              "rotation": [
                0,
                -45,
                0
              ]
            },
            {
              "origin": [
                -6.5837162377057155,
                -3.035239398331657,
                22.691894428838165
              ],
              "size": [
                4.000000000000002,
                2.999999999999999,
                6.999999999999993
              ],
              "uv": {
                "north": {
                  "uv": [
                    148,
                    24
                  ],
                  "uv_size": [
                    4,
                    3
                  ]
                },
                "east": {
                  "uv": [
                    140,
                    4
                  ],
                  "uv_size": [
                    7,
                    3
                  ]
                },
                "south": {
                  "uv": [
                    148,
                    20
                  ],
                  "uv_size": [
                    4,
                    3
                  ]
                },
                "west": {
                  "uv": [
                    140,
                    19
                  ],
                  "uv_size": [
                    7,
                    3
                  ]
                },
                "up": {
                  "uv": [
                    130,
                    28
                  ],
                  "uv_size": [
                    4,
                    7
                  ]
                },
                "down": {
                  "uv": [
                    32,
                    130
                  ],
                  "uv_size": [
                    4,
                    7
                  ]
                }
              },
              "pivot": [
                -13.483716237705726,
                -1.5352393983316597,
                15.191894428838168
              ],
              "rotation": [
                0,
                45,
                0
              ]
            },
            {
              "origin": [
                1.6483693285910794,
                -3.0352393983316563,
                11.565905898420958
              ],
              "size": [
                4.000000000000003,
                2.9999999999999987,
                9.00000000000001
              ],
              "uv": {
                "north": {
                  "uv": [
                    42,
                    148
                  ],
                  "uv_size": [
                    4,
                    3
                  ]
                },
                "east": {
                  "uv": [
                    132,
                    122
                  ],
                  "uv_size": [
                    9,
                    3
                  ]
                },
                "south": {
                  "uv": [
                    37,
                    148
                  ],
                  "uv_size": [
                    4,
                    3
                  ]
                },
                "west": {
                  "uv": [
                    132,
                    126
                  ],
                  "uv_size": [
                    9,
                    3
                  ]
                },
                "up": {
                  "uv": [
                    127,
                    122
                  ],
                  "uv_size": [
                    4,
                    9
                  ]
                },
                "down": {
                  "uv": [
                    22,
                    128
                  ],
                  "uv_size": [
                    4,
                    9
                  ]
                }
              },
              "pivot": [
                -13.25163067140892,
                -1.5352393983316597,
                16.06590589842097
              ],
              "inflate": 0.01
            }
          ]
        }
      ]
    }
  ]
}
